{
  "topic": "日間照顧",
  "source_type": "practical_summary",
  "aliases": [
    "日照",
    "日照中心",
    "日間照顧服務",
    "日間照顧中心",
    "BB碼"
  ],
  "summary": "日間照顧服務屬「照顧及專業服務」之內容之一（第八條第一項第二款），其照顧組合為附表四之BB碼，分全日與半日、第一型至第七型（BB01至BB14）。服務由完成長期照顧服務人員訓練認證繼續教育及登錄之照顧服務人員提供（第十八條第二款）。額度與「照顧及專業服務」共用，依長照需要等級規定於附表二。115年修正後，聘僱外籍看護者之百分之三十額度亦得用於日間照顧（第十條第二項）。",
  "common_questions": [
    "日間照顧有哪些照顧組合碼",
    "日照分全日和半日嗎",
    "聘外籍看護可以用日間照顧嗎",
    "日照的額度怎麼算"
  ],
  "related_articles": [7, 8, 10, 18],
  "related_codes": [
    "BB01", "BB02", "BB03", "BB04", "BB05", "BB06", "BB07",
    "BB08", "BB09", "BB10", "BB11", "BB12", "BB13", "BB14"
  ],
  "related_appendices": ["2", "4"],
  "related_topics": ["家庭托顧", "外籍看護", "外籍看護與日照", "喘息服務"],
  "keywords": [
    "日間照顧",
    "日照",
    "全日",
    "半日",
    "照顧及專業服務",
    "BB碼",
    "照顧服務人員"
  ],
  "law_source_note": "summary 依據 article-08（照顧及專業服務內容）、article-18（人員資格）、article-10（外籍看護額度放寬）、appendix-04（BB 碼）、appendix-02（額度）。"
}
